testrail_yak/__init__.py
testrail_yak/attachment.py
testrail_yak/case.py
testrail_yak/case_field.py
testrail_yak/case_type.py
testrail_yak/configuration.py
testrail_yak/milestone.py
testrail_yak/plan.py
testrail_yak/priority.py
testrail_yak/project.py
testrail_yak/report.py
testrail_yak/result.py
testrail_yak/result_field.py
testrail_yak/run.py
testrail_yak/section.py
testrail_yak/status.py
testrail_yak/suite.py
testrail_yak/template.py
testrail_yak/test.py
testrail_yak/user.py
testrail_yak/lib/__init__.py
testrail_yak/lib/schema.py
testrail_yak/lib/testrail.py
testrail_yak-2.0.4.dist-info/LICENSE
testrail_yak-2.0.4.dist-info/METADATA
testrail_yak-2.0.4.dist-info/WHEEL
testrail_yak-2.0.4.dist-info/top_level.txt
testrail_yak-2.0.4.dist-info/RECORD
