Metadata-Version: 2.1
Name: testrail-yak
Version: 2.0.4
Summary: Python library for interacting with the TestRail API, built on top of gurock's
Home-page: https://github.com/bbeale/TestRailYak
Author: bbeale
Author-email: beale.ben@gmail.com
License: Copyright (c) 2020 bbeale
Requires-Dist: urllib3
Requires-Dist: requests
Requires-Dist: marshmallow
